geohash_to_geojson/__init__.py
geohash_to_geojson/geohash_to_geojson.py
geohash_to_geojson-1.3.2.dist-info/LICENSE
geohash_to_geojson-1.3.2.dist-info/METADATA
geohash_to_geojson-1.3.2.dist-info/WHEEL
geohash_to_geojson-1.3.2.dist-info/top_level.txt
geohash_to_geojson-1.3.2.dist-info/RECORD
