Metadata-Version: 2.1
Name: geohash-to-geojson
Version: 1.3.2
Summary: convert set of geohashes into a geojson boundaries files of the corresponding geohashes
Home-page: https://github.com/brings123/geohash-to-geojson
Author: Afraoucene Chakib
Author-email: fc_afraoucene@esi.dz
License: MIT
Platform: UNKNOWN
Classifier: Programming Language :: Python :: 3
Classifier: License :: OSI Approved :: MIT License
Classifier: Operating System :: OS Independent
Requires-Dist: polygon-geohasher
Requires-Dist: geopandas
Requires-Dist: shapely
